elmawebapi/__init__.py
elmawebapi/api.py
elmawebapi/library.py
elmawebapi/structure.py
elmawebapi/services/__init__.py
elmawebapi/services/auth.py
elmawebapi/services/base.py
elmawebapi/services/decorators.py
elmawebapi/services/entity.py
elmawebapi/services/error.py
elmawebapi/services/feed.py
elmawebapi/services/files.py
elmawebapi/services/task.py
elmawebapi/services/workflow.py
ElmaWebAPI-0.1.3.dist-info/LICENSE
ElmaWebAPI-0.1.3.dist-info/METADATA
ElmaWebAPI-0.1.3.dist-info/WHEEL
ElmaWebAPI-0.1.3.dist-info/top_level.txt
ElmaWebAPI-0.1.3.dist-info/RECORD
