Metadata-Version: 2.1
Name: ElmaWebAPI
Version: 0.1.3
Summary: Using Elma3 Web API from python
Author-email: Ilya Chechetkin <illaech@gmail.com>
License: BSD 3-Clause License
Project-URL: Homepage, https://github.com/SovetnikProf/ElmaWebAPI/
Project-URL: Bug Tracker, https://github.com/SovetnikProf/ElmaWebAPI/issues/
Classifier: Programming Language :: Python :: 3.10
Classifier: Development Status :: 3 - Alpha
Classifier: License :: OSI Approved :: BSD License
Classifier: Natural Language :: Russian
Classifier: Operating System :: OS Independent
Classifier: Topic :: Utilities
Requires-Python: >=3.10
License-File: LICENSE
Requires-Dist: requests (~=2.28)
Provides-Extra: dev
Requires-Dist: ipython (~=8.4) ; extra == 'dev'
Requires-Dist: black (~=22.8) ; extra == 'dev'
Requires-Dist: isort (~=5.10) ; extra == 'dev'
Provides-Extra: tests
Requires-Dist: pytest (~=7.1) ; extra == 'tests'
Requires-Dist: pytest-cov (~=3.0) ; extra == 'tests'
Requires-Dist: pylint (~=2.15) ; extra == 'tests'
Requires-Dist: coverage-badge (~=1.1.0) ; extra == 'tests'
